simpel_themes/__init__.py
simpel_themes/admin.py
simpel_themes/apps.py
simpel_themes/hooks.py
simpel_themes/models.py
simpel_themes/settings.py
simpel_themes/tests.py
simpel_themes/urls.py
simpel_themes/utils.py
simpel_themes/version.py
simpel_themes/views.py
simpel_themes/api/__init__.py
simpel_themes/api/serializers.py
simpel_themes/api/views.py
simpel_themes/api/viewsets.py
simpel_themes/migrations/0001_initial.py
simpel_themes/migrations/0002_auto_20220321_2315.py
simpel_themes/migrations/0003_alter_modeltemplate_thumbnail.py
simpel_themes/migrations/0004_alter_screenshoot_template.py
simpel_themes/migrations/__init__.py
simpel_themes/templates/admin/simpel_themes/.gitinclude
simpel_themes/templates/simpel_themes/.gitinclude
simpel_themes-0.1.5.dist-info/LICENSE
simpel_themes-0.1.5.dist-info/METADATA
simpel_themes-0.1.5.dist-info/WHEEL
simpel_themes-0.1.5.dist-info/top_level.txt
simpel_themes-0.1.5.dist-info/RECORD
